[
  {
    "name": "S.A.M.",
    "members": [
      "Bear",
      "Lep"
    ],
    "current": {
      "rank": 1,
      "points": 1160,
      "season_points": 100,
      "wins": 3,
      "losses": 1,
      "tourn_won": 1
    },
    "career": {
      "rank": 1,
      "wins": 19,
      "losses": 7,
      "tourn_won": 11,
      "nye_wins": 1,
      "year_end_1": 2
    },
    "h2h": [
      [
        "Rock of Gibraltar",
        "5-0"
      ],
      [
        "Free Will",
        "8-7"
      ],
      [
        "Fire Breathing Rubber Duckies",
        "5-0"
      ],
      [
        "Size Matters",
        "0-0"
      ]
    ]
  },
  {
    "name": "Free Will",
    "members": [
      "Lacy",
      "Marissa"
    ],
    "current": {
      "rank": 2,
      "points": 1080,
      "season_points": 60,
      "wins": 2,
      "losses": 2,
      "tourn_won": 0
    },
    "career": {
      "rank": 2,
      "wins": 18,
      "losses": 11,
      "tourn_won": 2,
      "nye_wins": 1,
      "year_end_1": 0
    },
    "h2h": [
      [
        "S.A.M.",
        "7-8"
      ],
      [
        "Rock of Gibraltar",
        "5-3"
      ],
      [
        "Fire Breathing Rubber Duckies",
        "4-0"
      ],
      [
        "Size Matters",
        "1-0"
      ]
    ]
  },
  {
    "name": "Rock of Gibraltar",
    "members": [
      "Woodsy",
      "Rev"
    ],
    "current": {
      "rank": 3,
      "points": 290,
      "season_points": 10,
      "wins": 0,
      "losses": 2,
      "tourn_won": 0
    },
    "career": {
      "rank": 2,
      "wins": 7,
      "losses": 12,
      "tourn_won": 0,
      "nye_wins": 0,
      "year_end_1": 0
    },
    "h2h": [    
      [
        "S.A.M.",
        "0-5"
      ],
      [
        "Free Will",
        "3-5"
      ],
      [
        "Fire Breathing Rubber Duckies",
        "1-2"
      ],
      [
        "Size Matters",
        "2-0"
      ]
    ]
  },
  {
    "name": "Fire Breathing Rubber Duckies",
    "members": [
      "Kevin",
      "Katelyn"
    ],
    "current": {
      "rank": 4,
      "points": 265,
      "season_points": 0,
      "wins": 0,
      "losses": 0,
      "tourn_won": 0
    },
    "career": {
      "rank": 4,
      "wins": 5,
      "losses": 10,
      "tourn_won": 0,
      "nye_wins": 0,
      "year_end_1": 0
    },
    "h2h": [
      [
        "S.A.M.",
        "0-5"
      ],
      [
        "Rock of Gibraltar",
        "2-1"
      ],
      [
        "Free Will",
        "0-4"
      ],
      [
        "Size Matters",
        "2-0"
      ]
    ]
  }
]
