[
  {
    "name": "Lacy",
    "team": "Free Will",
    "position": "striker",
    "currentStats": {
      "gm": 0,
      "w": 0,
      "winPercentage": 0.0,
      "PP": 0,
      "g": 0,
      "ggm": 0.00,
      "ga": 0,
      "gagm": 0,
      "og": 0
    },
    "careerStats": {
      "gm": 25,
      "w": 16,
      "winPercentage": 0.640,
      "PP": 378,
      "g": 144,
      "ggm": 5.71,
      "ga": 0,
      "gagm": 0,
      "og": 1
    }
  },
  {
    "name": "Bear",
    "team": "S.A.M.",
    "position": "striker",
    "currentStats": {
      "gm": 0,
      "w": 0,
      "winPercentage": 0.000,
      "PP": 0,
      "g": 0,
      "ggm": 0.00,
      "ga": 0,
      "gagm": 0,
      "og": 0
    },
    "careerStats": {
      "gm": 22,
      "w": 16,
      "winPercentage": 0.727,
      "PP": 338,
      "g": 116,
      "ggm": 5.15,
      "ga": 0,
      "gagm": 0,
      "og": 0
    }
  },
  {
    "name": "Woodsy",
    "team": "Rock of Gibraltar",
    "position": "striker",
    "currentStats": {
      "gm": 0,
      "w": 0,
      "winPercentage": 0.000,
      "PP": 0,
      "g": 0,
      "ggm": 0.00,
      "ga": 0,
      "gagm": 0,
      "og": 0
    },
    "careerStats": {
      "gm": 20,
      "w": 8,
      "winPercentage": 0.400,
      "PP": 293,
      "g": 86,
      "ggm": 4.40,
      "ga": 0,
      "gagm": 0,
      "og": 0
    }
  },
  {
    "name": "Kevin",
    "team": "Fire Breathing Rubber Duckies",
    "position": "striker",
    "currentStats": {
      "gm": 0,
      "w": 0,
      "winPercentage": 0.000,
      "PP": 0,
      "g": 0,
      "ggm": 0.00,
      "ga": 0,
      "gagm": 0,
      "og": 0
    },
    "careerStats": {
      "gm": 18,
      "w": 6,
      "winPercentage": 0.333,
      "PP": 242,
      "g": 71,
      "ggm": 4.40,
      "ga": 0,
      "gagm": 0,
      "og": 1
    }
  },
  {
    "name": "Lep",
    "team": "S.A.M.",
    "position": "goalkeeper",
    "currentStats": {
      "gm": 0,
      "w": 0,
      "winPercentage": 0.000,
      "PP": 0,
      "g": 0,
      "ggm": 0.00,
      "ga": 0,
      "gagm": 0.00,
      "og": 0
    },
    "careerStats": {
      "gm": 22,
      "w": 16,
      "winPercentage": 0.727,
      "PP": 338,
      "g": 69,
      "ggm": 3.06,
      "ga": 143,
      "gagm": 6.35,
      "og": 2
    }
  },
  {
    "name": "Marissa",
    "team": "Free Will",
    "position": "goalkeeper",
    "currentStats": {
      "gm": 0,
      "w": 0,
      "winPercentage": 0.000,
      "PP": 0,
      "g": 0,
      "ggm": 0.00,
      "ga": 0,
      "gagm": 0.00,
      "og": 0
    },
    "careerStats": {
      "gm": 25,
      "w": 16,
      "winPercentage": 0.640,
      "PP": 378,
      "g": 56,
      "ggm": 2.22,
      "ga": 161,
      "gagm": 6.39,
      "og": 9
    }
  },
  {
    "name": "Rev",
    "team": "Rock of Gibraltar",
    "position": "goalkeeper",
    "currentStats": {
      "gm": 0,
      "w": 0,
      "winPercentage": 0.000,
      "PP": 0,
      "g": 0,
      "ggm": 0.00,
      "ga": 0,
      "gagm": 0.00,
      "og": 0
    },
    "careerStats": {
      "gm": 14,
      "w": 6,
      "winPercentage": 0.429,
      "PP": 204,
      "g": 39,
      "ggm": 2.87,
      "ga": 92,
      "gagm": 6.76,
      "og": 2
    }
  },
  {
    "name": "Woodsy",
    "team": "Rock of Gibraltar",
    "position": "goalkeeper",
    "currentStats": {
      "gm": 0,
      "w": 0,
      "winPercentage": 0.000,
      "PP": 0,
      "g": 0,
      "ggm": 0.00,
      "ga": 0,
      "gagm": 0.00,
      "og": 0
    },
    "careerStats": {
      "gm": 3,
      "w": 1,
      "winPercentage": 0.333,
      "PP": 46,
      "g": 6,
      "ggm": 1.96,
      "ga": 26,
      "gagm": 8.48,
      "og": 0
    }
  },
  {
    "name": "Katelyn",
    "team": "Fire Breathing Rubber Duckies",
    "position": "goalkeeper",
    "currentStats": {
      "gm": 0,
      "w": 0,
      "winPercentage": 0.000,
      "PP": 0,
      "g": 0,
      "ggm": 0.00,
      "ga": 0,
      "gagm": 0.00,
      "og": 0
    },
    "careerStats": {
      "gm": 15,
      "w": 5,
      "winPercentage": 0.333,
      "PP": 199,
      "g": 12,
      "ggm": 0.90,
      "ga": 120,
      "gagm": 9.06,
      "og": 2
    }
  }
]
